{
  "schemaVersion": 1,
  "updatedAt": "2025-11-05T12:00:00Z",
  "language": "uk",
  "articles": [
    {
      "id": "3ab4bbb3-7832-41a9-ab68-d639ca3e6f1e",
      "title": "Введення алергенів у прикорм дитини",
      "teaser": "Чому контрольоване знайомство з алергенами у 6 місяців допомагає зменшити ризик реакцій.",
      "cover": {
        "url": "https://tverdokhlibk.github.io/kostyatverdokhlib.github.io-blw-blog/images/allergy.webp",
        "caption": "Алергенні продукти у раціоні немовляти"
      },
      "blocks": [
        {
          "type": "paragraph",
          "data": {
            "text": "Алергія у дітей — одна з найпоширеніших проблем раннього віку. Раніше лікарі радили уникати алергенів у раціоні немовлят, але сучасні дослідження доводять, що своєчасне введення алергенних продуктів допомагає знизити ризик розвитку алергії."
          }
        },
        {
          "type": "divider"
        },
        {
          "type": "heading",
          "data": {
            "text": "Сучасний підхід"
          }
        },
        {
          "type": "paragraph",
          "data": {
            "text": "Міжнародні організації — ВООЗ, ESPGHAN та Американська академія педіатрії — радять починати знайомство з алергенами приблизно з 6 місяців, коли дитина вже готова до твердої їжі."
          }
        },
        {
          "type": "paragraph",
          "data": {
            "text": "«Раннє знайомство з невеликими дозами алергенів сприяє формуванню імунної толерантності», — підкреслюють експерти."
          }
        },
        {
          "type": "paragraph",
          "data": {
            "text": "Перед кожним новим продуктом переконайтеся, що малюк здоровий, без висипань чи застуди. Вводьте лише один алерген за раз, щоб легко відстежити можливу реакцію."
          }
        },
        {
          "type": "divider"
        },
        {
          "type": "heading",
          "data": {
            "text": "Основні харчові алергени"
          }
        },
        {
          "type": "paragraph",
          "data": {
            "text": "У ЄС офіційно визначено 14 груп харчових алергенів: глютен, арахіс, горіхи, селера, гірчиця, молоко, яйця, кунжут, риба, ракоподібні, молюски, соя, сульфіти та люпін."
          }
        },
        {
          "type": "paragraph",
          "data": {
            "text": "Для українського прикорму найчастіше актуальні яйця, риба, молоко, пшениця, соя, арахіс, селера, горіхи та кунжут."
          }
        },
        {
          "type": "divider"
        },
        {
          "type": "heading",
          "data": {
            "text": "Як починати знайомство з алергенами"
          }
        },
        {
          "type": "paragraph",
          "data": {
            "text": "Після того як дитина звикла до базових продуктів — овочів, каш і м'яса — можна поступово додавати алергенні продукти з мікропорцій."
          }
        },
        {
          "type": "paragraph",
          "data": {
            "text": "Поради:"
          }
        },
        {
          "type": "paragraph",
          "data": {
            "text": "• Починайте з мікропорцій — 1/4 чайної ложки або кількох крупинок."
          }
        },
        {
          "type": "paragraph",
          "data": {
            "text": "• Якщо реакції немає, поступово збільшуйте кількість протягом кількох днів."
          }
        },
        {
          "type": "paragraph",
          "data": {
            "text": "• Між новими продуктами витримуйте щонайменше 3 дні спостереження."
          }
        },
        {
          "type": "divider"
        },
        {
          "type": "heading",
          "data": {
            "text": "Як безпечно вводити алергени"
          }
        },
        {
          "type": "paragraph",
          "data": {
            "text": "1. Лише один новий продукт за раз."
          }
        },
        {
          "type": "paragraph",
          "data": {
            "text": "2. Починайте з мінімальної кількості."
          }
        },
        {
          "type": "paragraph",
          "data": {
            "text": "3. Уникайте інших новинок протягом трьох днів."
          }
        },
        {
          "type": "paragraph",
          "data": {
            "text": "4. Пропонуйте вдень, щоб спостерігати за реакцією."
          }
        },
        {
          "type": "paragraph",
          "data": {
            "text": "5. Якщо переноситься добре, повторюйте 1–2 рази на тиждень."
          }
        },
        {
          "type": "divider"
        },
        {
          "type": "heading",
          "data": {
            "text": "Можливі прояви алергії"
          }
        },
        {
          "type": "paragraph",
          "data": {
            "text": "Сигнали, на які варто звернути увагу:"
          }
        },
        {
          "type": "paragraph",
          "data": {
            "text": "• Почервоніння або висип навколо рота."
          }
        },
        {
          "type": "paragraph",
          "data": {
            "text": "• Набряк губ, повік чи обличчя."
          }
        },
        {
          "type": "paragraph",
          "data": {
            "text": "• Кашель, чхання або утруднене дихання."
          }
        },
        {
          "type": "paragraph",
          "data": {
            "text": "• Діарея, блювання чи виражені коліки."
          }
        },
        {
          "type": "paragraph",
          "data": {
            "text": "• Різка примхливість, свербіж або занепокоєння."
          }
        },
        {
          "type": "paragraph",
          "data": {
            "text": "Якщо виникли важкі симптоми, особливо набряк або утруднене дихання, негайно зверніться до лікаря."
          }
        },
        {
          "type": "divider"
        },
        {
          "type": "heading",
          "data": {
            "text": "Якщо алергія вже була"
          }
        },
        {
          "type": "paragraph",
          "data": {
            "text": "Не вводьте продукт повторно без консультації з лікарем. Лише спеціаліст визначить безпечну стратегію повторного знайомства."
          }
        },
        {
          "type": "paragraph",
          "data": {
            "text": "Деякі діти можуть «перерости» алергію, але повторні спроби проводьте лише під контролем алерголога."
          }
        },
        {
          "type": "divider"
        },
        {
          "type": "heading",
          "data": {
            "text": "Головна думка"
          }
        },
        {
          "type": "paragraph",
          "data": {
            "text": "Алергени — не вороги, якщо вводити їх розумно та поступово. Контрольоване знайомство з новими продуктами формує здорові харчові звички й зменшує ризик алергії в майбутньому."
          }
        }
      ]
    },
    {
      "id": "3f91c5db-5f06-4e36-9d2c-2b9188cbf65c",
      "title": "Коли починати прикорм: ознаки готовності дитини",
      "teaser": "Як визначити готовність малюка до першого прикорму та обрати вдалий момент.",
      "cover": {
        "url": "https://tverdokhlibk.github.io/kostyatverdokhlib.github.io-blw-blog/images/1.webp",
        "caption": "Перші ложечки прикорму для зацікавленого малюка"
      },
      "blocks": [
        {
          "type": "paragraph",
          "data": {
            "text": "Перший прикорм — це важливий етап у розвитку малюка, коли він переходить від виключно грудного молока або суміші до нових продуктів. Від правильного часу початку прикорму залежить не лише апетит, а й формування травної системи, розвиток смакових звичок та навіть майбутнє ставлення до їжі."
          }
        },
        {
          "type": "heading",
          "data": {
            "text": "Оптимальний вік для початку прикорму"
          }
        },
        {
          "type": "paragraph",
          "data": {
            "text": "За рекомендаціями Всесвітньої організації охорони здоров'я (ВООЗ) і педіатрів більшості країн, прикорм слід вводити у віці близько 6 місяців. До цього часу грудне молоко або адаптована суміш повністю забезпечують дитину необхідними поживними речовинами."
          }
        },
        {
          "type": "paragraph",
          "data": {
            "text": "Втім, деякі діти можуть бути готові трохи раніше — у 5 місяців, а інші — лише ближче до 7 місяців. Головне не поспішати, а орієнтуватися не лише на вік, а й на ознаки готовності дитини."
          }
        },
        {
          "type": "divider"
        },
        {
          "type": "heading",
          "data": {
            "text": "Ознаки готовності малюка до прикорму"
          }
        },
        {
          "type": "paragraph",
          "data": {
            "text": "Кожна дитина розвивається у своєму темпі, тому важливо спостерігати за поведінкою малюка. Нижче наведено ключові сигнали, які свідчать, що час знайомити його з новими смаками."
          }
        },
        {
          "type": "heading",
          "data": {
            "text": "1. Дитина впевнено тримає голову"
          }
        },
        {
          "type": "paragraph",
          "data": {
            "text": "Малюк має самостійно утримувати голову прямо та сидіти з мінімальною підтримкою. Це важливо для безпеки — щоб не було ризику захлинання під час їжі."
          }
        },
        {
          "type": "heading",
          "data": {
            "text": "2. Цікавиться їжею дорослих"
          }
        },
        {
          "type": "paragraph",
          "data": {
            "text": "Якщо дитина з цікавістю спостерігає за тим, як ви їсте, тягнеться ручками до ложки або намагається взяти шматочок, це ознака готовності до знайомства з новими смаками."
          }
        },
        {
          "type": "heading",
          "data": {
            "text": "3. Зник рефлекс виштовхування язиком"
          }
        },
        {
          "type": "paragraph",
          "data": {
            "text": "Новонароджені мають природний рефлекс виштовхування, коли будь-що твердіше молока дитина автоматично виштовхує язиком. Якщо цей рефлекс зникає — дитина вже може ковтати пюреподібну їжу."
          }
        },
        {
          "type": "heading",
          "data": {
            "text": "4. Збільшився апетит і дитині не вистачає молока"
          }
        },
        {
          "type": "paragraph",
          "data": {
            "text": "Якщо малюк частіше просить їсти, але виглядає незадоволеним після годування, це може бути сигналом, що організму вже потрібно більше поживних речовин."
          }
        },
        {
          "type": "heading",
          "data": {
            "text": "5. Подвоєння ваги від народження"
          }
        },
        {
          "type": "paragraph",
          "data": {
            "text": "Орієнтиром готовності є також подвоєння маси тіла від моменту народження. Це свідчить, що дитячий організм активно росте й потребує додаткової енергії."
          }
        },
        {
          "type": "heading",
          "data": {
            "text": "6. Відсутність ознак хвороби"
          }
        },
        {
          "type": "paragraph",
          "data": {
            "text": "Починати прикорм варто лише тоді, коли дитина здорова, не має застуди, проблем зі шлунком чи прорізування зубів, які можуть викликати тимчасову відмову від нової їжі."
          }
        },
        {
          "type": "divider"
        },
        {
          "type": "heading",
          "data": {
            "text": "Коли не варто починати прикорм"
          }
        },
        {
          "type": "paragraph",
          "data": {
            "text": "Не вводьте нові продукти, якщо дитина хворіє або нещодавно отримала щеплення."
          }
        },
        {
          "type": "paragraph",
          "data": {
            "text": "Уникайте старту прикорму в період сильної спеки через ризик зневоднення."
          }
        },
        {
          "type": "paragraph",
          "data": {
            "text": "Відкладіть знайомство з їжею, коли спостерігаєте сильний стрес чи зміни в режимі, наприклад переїзд або поява нової няні."
          }
        },
        {
          "type": "paragraph",
          "data": {
            "text": "Почекайте, якщо малюк ще не тримає голову або не сидить самостійно."
          }
        },
        {
          "type": "divider"
        },
        {
          "type": "heading",
          "data": {
            "text": "Як підготуватися до першого прикорму"
          }
        },
        {
          "type": "paragraph",
          "data": {
            "text": "1. Обирайте правильний час доби — коли дитина активна, не надто голодна й у гарному настрої."
          }
        },
        {
          "type": "paragraph",
          "data": {
            "text": "2. Починайте з одного продукту і спостерігайте за реакцією протягом 2–3 днів."
          }
        },
        {
          "type": "paragraph",
          "data": {
            "text": "3. Не примушуйте — якщо дитина відвертається або стискає губи, просто спробуйте пізніше."
          }
        },
        {
          "type": "paragraph",
          "data": {
            "text": "4. Подавайте їжу ложкою, а не з пляшечки — так дитина вчиться правильно ковтати."
          }
        },
        {
          "type": "paragraph",
          "data": {
            "text": "5. Записуйте спостереження — ведіть невеликий щоденник прикорму або використовуйте для цього мобільний додаток."
          }
        },
        {
          "type": "divider"
        },
        {
          "type": "heading",
          "data": {
            "text": "Ранні чи пізні прикорми: чому важливо знайти баланс"
          }
        },
        {
          "type": "paragraph",
          "data": {
            "text": "Занадто ранній прикорм, до 4 місяців, може перевантажити травну систему, збільшити ризик алергії та проблем зі шлунком."
          }
        },
        {
          "type": "paragraph",
          "data": {
            "text": "Занадто пізній прикорм, після 8 місяців, може призвести до нестачі заліза, відмови від твердої їжі й затримки формування жувального рефлексу."
          }
        },
        {
          "type": "paragraph",
          "data": {
            "text": "Тому найкраща стратегія — орієнтуватися на готовність дитини, а не на строгі дати в календарі."
          }
        },
        {
          "type": "paragraph",
          "data": {
            "text": "Початок прикорму — це не лише про їжу, а про новий крок у розвитку дитини. Коли ви помічаєте ознаки готовності, знайомте малюка з новими смаками повільно, з турботою та інтересом."
          }
        },
        {
          "type": "paragraph",
          "data": {
            "text": "Пам'ятайте: кожна ложечка — це маленьке відкриття, шлях до самостійності й нових відчуттів."
          }
        }
      ]
    },
    {
      "id": "f7ddca56-f196-4524-bb21-51b5a63a40f3",
      "title": "Перші продукти для прикорму: що вибрати спочатку",
      "teaser": "Розбираємо, з яких овочів чи каш варто почати перший прикорм і як безпечно знайомити малюка з новими смаками.",
      "cover": {
        "url": "https://tverdokhlibk.github.io/kostyatverdokhlib.github.io-blw-blog/images/2.webp",
        "caption": "Пюре та каші як перші страви для прикорму"
      },
      "blocks": [
        {
          "type": "paragraph",
          "data": {
            "text": "Початок прикорму — це новий етап у житті малюка і важливий крок для батьків. Після перших шести місяців життя дитині вже стає недостатньо поживних речовин з грудного молока чи суміші, тому вона поступово потребує додаткових продуктів. Але з чого почати, щоб усе пройшло безпечно та з користю?"
          }
        },
        {
          "type": "divider"
        },
        {
          "type": "heading",
          "data": {
            "text": "Який продукт обрати першим"
          }
        },
        {
          "type": "paragraph",
          "data": {
            "text": "Є кілька варіантів, з чого почати прикорм, і вибір часто залежить від стану здоров'я, темпів набору ваги та рекомендацій лікаря. Педіатри зазвичай радять починати з однокомпонентних овочевих або злакових пюре, щоб організм дитини міг поступово адаптуватися."
          }
        },
        {
          "type": "heading",
          "data": {
            "text": "Варіант 1. Овочеве пюре"
          }
        },
        {
          "type": "paragraph",
          "data": {
            "text": "Ідеально підходить для дітей, які мають надлишкову вагу або добре додають у масі."
          }
        },
        {
          "type": "paragraph",
          "data": {
            "text": "Першими овочами зазвичай стають:"
          }
        },
        {
          "type": "paragraph",
          "data": {
            "text": "- кабачок;"
          }
        },
        {
          "type": "paragraph",
          "data": {
            "text": "- цвітна капуста;"
          }
        },
        {
          "type": "paragraph",
          "data": {
            "text": "- броколі;"
          }
        },
        {
          "type": "paragraph",
          "data": {
            "text": "- гарбуз."
          }
        },
        {
          "type": "paragraph",
          "data": {
            "text": "Вони легкі для травлення, рідко викликають алергію і мають ніжний смак, близький до грудного молока. Пюре слід готувати без солі та спецій, починаючи з 1–2 чайних ложок на день."
          }
        },
        {
          "type": "heading",
          "data": {
            "text": "Варіант 2. Каші без глютену"
          }
        },
        {
          "type": "paragraph",
          "data": {
            "text": "Якщо дитина повільно набирає вагу або є ознаки нестачі енергії, першим продуктом можуть бути однокомпонентні безмолочні каші:"
          }
        },
        {
          "type": "paragraph",
          "data": {
            "text": "- рисова;"
          }
        },
        {
          "type": "paragraph",
          "data": {
            "text": "- гречана;"
          }
        },
        {
          "type": "paragraph",
          "data": {
            "text": "- кукурудзяна."
          }
        },
        {
          "type": "paragraph",
          "data": {
            "text": "Кашу можна приготувати на воді або розвести грудним молоком чи адаптованою сумішшю. Головне — без цукру, солі й добавок."
          }
        },
        {
          "type": "heading",
          "data": {
            "text": "Варіант 3. Фруктове пюре"
          }
        },
        {
          "type": "paragraph",
          "data": {
            "text": "Фрукти мають приємний смак і дитина швидко звикає до них, але з ними краще не поспішати. Їх рекомендують після овочів, щоб малюк не відмовлявся від менш солодких страв."
          }
        },
        {
          "type": "paragraph",
          "data": {
            "text": "Для початку підійдуть:"
          }
        },
        {
          "type": "paragraph",
          "data": {
            "text": "- яблуко;"
          }
        },
        {
          "type": "paragraph",
          "data": {
            "text": "- груша;"
          }
        },
        {
          "type": "paragraph",
          "data": {
            "text": "- банан (з 7 місяців)."
          }
        },
        {
          "type": "divider"
        },
        {
          "type": "heading",
          "data": {
            "text": "Як вводити перші продукти"
          }
        },
        {
          "type": "paragraph",
          "data": {
            "text": "1. Починайте з одного інгредієнта. Новий продукт вводять окремо, щоб легше відстежити реакцію організму."
          }
        },
        {
          "type": "paragraph",
          "data": {
            "text": "2. Поступово збільшуйте кількість. Почніть з 1 чайної ложки, поступово доводячи до повної порції до 100–150 г на день."
          }
        },
        {
          "type": "paragraph",
          "data": {
            "text": "3. Спостерігайте за реакцією. Якщо немає висипів, болю в животі чи змін у стулі, через 3–4 дні можна додавати інший продукт."
          }
        },
        {
          "type": "paragraph",
          "data": {
            "text": "4. Готуйте без солі, цукру та спецій. Організму дитини достатньо природного смаку продуктів."
          }
        },
        {
          "type": "paragraph",
          "data": {
            "text": "5. Вибирайте правильний час. Найкраще давати нову їжу вдень — між ранковим і денним годуванням, коли малюк у гарному настрої."
          }
        },
        {
          "type": "divider"
        },
        {
          "type": "heading",
          "data": {
            "text": "Приклади першого меню"
          }
        },
        {
          "type": "paragraph",
          "data": {
            "text": "- День 1–3: пюре з кабачка — 1 ч. ложка → 3–4 ч. ложки."
          }
        },
        {
          "type": "paragraph",
          "data": {
            "text": "- День 4–6: пюре з цвітної капусти — 1 ч. ложка → 5 ч. ложок."
          }
        },
        {
          "type": "paragraph",
          "data": {
            "text": "- День 7–10: кабачок + цвітна капуста, або перехід до гречаної каші."
          }
        },
        {
          "type": "paragraph",
          "data": {
            "text": "З 7 місяців можна пробувати картоплю, моркву, гарбуз, яблуко, грушу, а потім і м'ясо."
          }
        },
        {
          "type": "divider"
        },
        {
          "type": "heading",
          "data": {
            "text": "Типові помилки під час початку прикорму"
          }
        },
        {
          "type": "paragraph",
          "data": {
            "text": "- Починати, коли дитина ще не сидить або не тримає голову."
          }
        },
        {
          "type": "paragraph",
          "data": {
            "text": "- Давати кілька нових продуктів одночасно."
          }
        },
        {
          "type": "paragraph",
          "data": {
            "text": "- Додавати сіль або цукор."
          }
        },
        {
          "type": "paragraph",
          "data": {
            "text": "- Примушувати їсти, коли дитина не хоче."
          }
        },
        {
          "type": "paragraph",
          "data": {
            "text": "- Пропонувати їжу під час хвороби чи після вакцинації."
          }
        },
        {
          "type": "paragraph",
          "data": {
            "text": "Пам'ятайте: прикорм — це не змагання, а процес знайомства зі світом нових смаків."
          }
        },
        {
          "type": "divider"
        },
        {
          "type": "heading",
          "data": {
            "text": "Коли звернутися до лікаря"
          }
        },
        {
          "type": "paragraph",
          "data": {
            "text": "Якщо після введення нового продукту ви помітили:"
          }
        },
        {
          "type": "paragraph",
          "data": {
            "text": "- висип або почервоніння;"
          }
        },
        {
          "type": "paragraph",
          "data": {
            "text": "- пронос чи запор;"
          }
        },
        {
          "type": "paragraph",
          "data": {
            "text": "- надмірне зригування;"
          }
        },
        {
          "type": "paragraph",
          "data": {
            "text": "- занепокоєння, порушення сну;"
          }
        },
        {
          "type": "paragraph",
          "data": {
            "text": "- набряки чи утруднене дихання — негайно припиніть прикорм і проконсультуйтеся з педіатром або алергологом."
          }
        },
        {
          "type": "divider"
        },
        {
          "type": "heading",
          "data": {
            "text": "Поради батькам"
          }
        },
        {
          "type": "paragraph",
          "data": {
            "text": "- Не забувайте, що грудне молоко або суміш залишаються основним харчуванням до 1 року."
          }
        },
        {
          "type": "paragraph",
          "data": {
            "text": "- Створіть позитивну атмосферу під час годування: усміхайтеся, говоріть спокійно."
          }
        },
        {
          "type": "paragraph",
          "data": {
            "text": "- Дозвольте дитині торкатися ложки та пробувати самостійно. Це розвиває інтерес і дрібну моторику."
          }
        },
        {
          "type": "paragraph",
          "data": {
            "text": "- Якщо щось не сподобалось — зробіть паузу на кілька днів і спробуйте знову."
          }
        },
        {
          "type": "divider"
        },
        {
          "type": "heading",
          "data": {
            "text": "Підсумок"
          }
        },
        {
          "type": "paragraph",
          "data": {
            "text": "Перші продукти прикорму мають бути простими, безпечними й натуральними. Почніть із овочів або каш, уважно спостерігайте за реакцією та вводьте нові страви поступово."
          }
        },
        {
          "type": "paragraph",
          "data": {
            "text": "Найголовніше — робіть усе спокійно, без поспіху, з любов'ю й турботою. Кожна нова ложечка — це крок дитини у великий світ дорослого харчування."
          }
        }
      ]
    },
    {
      "id": "7accabaa-306a-4267-8159-7b684cfec85d",
      "title": "БЛВ (BLW) або самоприкорм — сучасний підхід до введення прикорму",
      "teaser": "Що таке підхід BLW, як оцінити готовність дитини та організувати безпечний самоприкорм.",
      "cover": {
        "url": "https://tverdokhlibk.github.io/kostyatverdokhlib.github.io-blw-blog/images/3.webp",
        "caption": "Малюк вивчає тверду їжу самостійно під час першої трапези"
      },
      "blocks": [
        {
          "type": "heading",
          "data": {
            "text": "Що таке BLW"
          }
        },
        {
          "type": "paragraph",
          "data": {
            "text": "BLW (baby-led weaning) — це не тип прикорму, а підхід, який передбачає, що дитина сама бере участь у процесі годування з перших днів знайомства з твердою їжею."
          }
        },
        {
          "type": "paragraph",
          "data": {
            "text": "Ідею сформулювала Джилл Ріпли — британська медсестра, консультантка з грудного вигодовування та авторка досліджень."
          }
        },
        {
          "type": "paragraph",
          "data": {
            "text": "BLW набув популярності у світі завдяки своїй простій, але революційній ідеї:"
          }
        },
        {
          "type": "paragraph",
          "data": {
            "text": "“Дитина керує власним харчуванням, а дорослі створюють умови для безпечного й природного процесу.”"
          }
        },
        {
          "type": "divider"
        },
        {
          "type": "heading",
          "data": {
            "text": "Переваги самоприкорму"
          }
        },
        {
          "type": "paragraph",
          "data": {
            "text": "- формує здорову харчову поведінку з дитинства;"
          }
        },
        {
          "type": "paragraph",
          "data": {
            "text": "- розвиває координацію рухів та дрібну моторику;"
          }
        },
        {
          "type": "paragraph",
          "data": {
            "text": "- стимулює сенсорний розвиток через дотик, смак і запах;"
          }
        },
        {
          "type": "paragraph",
          "data": {
            "text": "- знижує ризик переїдання та вибірковості в їжі у майбутньому;"
          }
        },
        {
          "type": "paragraph",
          "data": {
            "text": "- сприяє емоційному зв’язку між дитиною та батьками під час трапези."
          }
        },
        {
          "type": "divider"
        },
        {
          "type": "heading",
          "data": {
            "text": "Коли можна починати БЛВ"
          }
        },
        {
          "type": "paragraph",
          "data": {
            "text": "Самоприкорм підходить дітям приблизно з 6 місяців, коли вони:"
          }
        },
        {
          "type": "paragraph",
          "data": {
            "text": "- можуть сидіти самостійно або з мінімальною підтримкою;"
          }
        },
        {
          "type": "paragraph",
          "data": {
            "text": "- впевнено тримають голову;"
          }
        },
        {
          "type": "paragraph",
          "data": {
            "text": "- здатні брати їжу руками і підносити до рота."
          }
        },
        {
          "type": "paragraph",
          "data": {
            "text": "Перед початком важливо переконатися, що дитина готова фізично — її травна система, навички жування та постуральна стабільність достатньо розвинені."
          }
        },
        {
          "type": "paragraph",
          "data": {
            "text": "Всесвітня організація охорони здоров’я також рекомендує починати введення прикорму після 6 місяців разом із продовженням грудного вигодовування."
          }
        },
        {
          "type": "divider"
        },
        {
          "type": "heading",
          "data": {
            "text": "Основні правила БЛВ"
          }
        },
        {
          "type": "paragraph",
          "data": {
            "text": "1. Безпека перш за все. Дитина має сидіти вертикально, щоб координувати ковтання й дихання."
          }
        },
        {
          "type": "paragraph",
          "data": {
            "text": "2. Не годуйте дитину з ложки. Вона має сама вирішувати, що, коли і скільки їсти."
          }
        },
        {
          "type": "paragraph",
          "data": {
            "text": "3. Не залишайте малюка без нагляду під час їжі."
          }
        },
        {
          "type": "paragraph",
          "data": {
            "text": "4. Не додавайте сіль, цукор, мед чи спеції."
          }
        },
        {
          "type": "paragraph",
          "data": {
            "text": "5. Їжа має бути м’якою, безпечної форми та розміру."
          }
        },
        {
          "type": "paragraph",
          "data": {
            "text": "6. Пропонуйте воду в чашці або склянці, а не з поїльника."
          }
        },
        {
          "type": "paragraph",
          "data": {
            "text": "7. Ніяких гаджетів чи телевізора під час їжі."
          }
        },
        {
          "type": "paragraph",
          "data": {
            "text": "8. Грудне молоко або суміш залишаються основною їжею до року."
          }
        },
        {
          "type": "divider"
        },
        {
          "type": "heading",
          "data": {
            "text": "Як організувати трапезу"
          }
        },
        {
          "type": "paragraph",
          "data": {
            "text": "- посадіть дитину у зручний стільчик із підніжкою;"
          }
        },
        {
          "type": "paragraph",
          "data": {
            "text": "- оберіть однотонний посуд без малюнків — це зменшує відволікання;"
          }
        },
        {
          "type": "paragraph",
          "data": {
            "text": "- використовуйте тарілку на присосці або силіконовий килимок;"
          }
        },
        {
          "type": "paragraph",
          "data": {
            "text": "- стеліть під стільчик клейонку чи серветку — безлад на початку неминучий;"
          }
        },
        {
          "type": "paragraph",
          "data": {
            "text": "- підготуйте силіконовий слюнявчик з кишенькою;"
          }
        },
        {
          "type": "paragraph",
          "data": {
            "text": "- подавайте продукти у вигляді довгих смужок або брусочків, товщиною з палець дорослого."
          }
        },
        {
          "type": "divider"
        },
        {
          "type": "heading",
          "data": {
            "text": "Безпечна подача продуктів"
          }
        },
        {
          "type": "paragraph",
          "data": {
            "text": "Перевірте консистенцію: якщо продукт легко розчавлюється пальцями — він безпечний."
          }
        },
        {
          "type": "paragraph",
          "data": {
            "text": "Почніть із м’яких овочів і фруктів: броколі, цвітна капуста, морква, кабачок, авокадо, банан, яблуко на парі."
          }
        },
        {
          "type": "paragraph",
          "data": {
            "text": "Поступово додавайте інші продукти — каші, м’ясо, бобові, яйця."
          }
        },
        {
          "type": "paragraph",
          "data": {
            "text": "Головне — не поспішати й вводити нові інгредієнти поступово, спостерігаючи за реакцією організму."
          }
        },
        {
          "type": "divider"
        },
        {
          "type": "heading",
          "data": {
            "text": "Ризик удавлення і природні рефлекси"
          }
        },
        {
          "type": "paragraph",
          "data": {
            "text": "Батьки часто бояться, що дитина подавиться. Але дослідження показують, що ризик задихання при BLW не вищий, ніж при традиційному годуванні пюре."
          }
        },
        {
          "type": "paragraph",
          "data": {
            "text": "У малюків є виштовхувальний (блювотний) рефлекс — природний захисний механізм, який не дозволяє шматочкам потрапити глибоко в горло."
          }
        },
        {
          "type": "paragraph",
          "data": {
            "text": "Важливо:"
          }
        },
        {
          "type": "paragraph",
          "data": {
            "text": "- не лізьте до рота дитині руками чи ложкою;"
          }
        },
        {
          "type": "paragraph",
          "data": {
            "text": "- не бийте по спині;"
          }
        },
        {
          "type": "paragraph",
          "data": {
            "text": "- спокійно дозвольте дитині відкашлятися;"
          }
        },
        {
          "type": "paragraph",
          "data": {
            "text": "- втручайтеся лише тоді, коли дитина не дихає, не видає звуків і синіє."
          }
        },
        {
          "type": "divider"
        },
        {
          "type": "heading",
          "data": {
            "text": "Що давати на початку"
          }
        },
        {
          "type": "paragraph",
          "data": {
            "text": "Для перших спроб ідеально підходять м’які продукти, які можна легко розчавити яснами:"
          }
        },
        {
          "type": "paragraph",
          "data": {
            "text": "- відварені овочі (морква, гарбуз, картопля, броколі);"
          }
        },
        {
          "type": "paragraph",
          "data": {
            "text": "- фрукти (банан, грушка, авокадо);"
          }
        },
        {
          "type": "paragraph",
          "data": {
            "text": "- м’яке м’ясо або фрикадельки;"
          }
        },
        {
          "type": "paragraph",
          "data": {
            "text": "- густі каші, сформовані у смужки;"
          }
        },
        {
          "type": "paragraph",
          "data": {
            "text": "- тости, макарони, яйце, риба — поступово, за віком."
          }
        },
        {
          "type": "divider"
        },
        {
          "type": "heading",
          "data": {
            "text": "Комбінування з ложкою"
          }
        },
        {
          "type": "paragraph",
          "data": {
            "text": "BLW не забороняє ложку, якщо дитина сама її тримає."
          }
        },
        {
          "type": "paragraph",
          "data": {
            "text": "Для початку підійдуть спеціальні pre-spoon ложки з невеликими заглибленнями."
          }
        },
        {
          "type": "paragraph",
          "data": {
            "text": "Важливо, щоб пюре було густим, а не рідким, аби дитина могла контролювати процес."
          }
        },
        {
          "type": "divider"
        },
        {
          "type": "heading",
          "data": {
            "text": "Коли БЛВ не підходить"
          }
        },
        {
          "type": "paragraph",
          "data": {
            "text": "Підхід не рекомендований дітям із:"
          }
        },
        {
          "type": "paragraph",
          "data": {
            "text": "- дисфагією (порушенням ковтання);"
          }
        },
        {
          "type": "paragraph",
          "data": {
            "text": "- гіпотонією або затримкою розвитку;"
          }
        },
        {
          "type": "paragraph",
          "data": {
            "text": "- анатомічними вадами ротової порожнини;"
          }
        },
        {
          "type": "paragraph",
          "data": {
            "text": "- низькою вагою, анемією або передчасним народженням (без дозволу педіатра)."
          }
        },
        {
          "type": "divider"
        },
        {
          "type": "heading",
          "data": {
            "text": "Міжнародний досвід і рекомендації"
          }
        },
        {
          "type": "paragraph",
          "data": {
            "text": "- ВООЗ наголошує, що прикорм слід розпочинати з 6 місяців, продовжуючи грудне вигодовування до 2 років або довше."
          }
        },
        {
          "type": "paragraph",
          "data": {
            "text": "- Американська академія педіатрії визнає BLW безпечним підходом за умови контролю з боку дорослих і правильного вибору консистенції їжі."
          }
        },
        {
          "type": "paragraph",
          "data": {
            "text": "- Національна служба охорони здоров’я Великої Британії зазначає, що самоприкорм допомагає дитині краще розпізнавати голод і ситість, розвиває самостійність."
          }
        },
        {
          "type": "paragraph",
          "data": {
            "text": "- Систематичні огляди BMJ Open та International Journal of Pediatrics підтверджують, що діти на BLW мають схожу поживну цінність раціону, але важливо стежити за надходженням заліза та уникати твердих шматочків."
          }
        },
        {
          "type": "divider"
        },
        {
          "type": "paragraph",
          "data": {
            "text": "BLW — це природний, уважний і поважний підхід до розвитку дитини."
          }
        },
        {
          "type": "paragraph",
          "data": {
            "text": "Він навчає самостійності, формує здорове ставлення до їжі й допомагає створити позитивну атмосферу під час трапез."
          }
        },
        {
          "type": "paragraph",
          "data": {
            "text": "Батькам важливо бути поруч, підтримувати й довіряти своєму малюкові."
          }
        },
        {
          "type": "paragraph",
          "data": {
            "text": "Адже головне завдання прикорму — не просто нагодувати, а навчити їсти з насолодою, впевненістю і безпекою ❤️."
          }
        }
      ]
    },
    {
      "id": "ee4443c2-eeb7-44b1-a5e7-315f8a7cb775",
      "title": "Введення алергенів у прикорм дитини",
      "teaser": "Як раннє та контрольоване знайомство з алергенами допомагає знизити ризик харчової алергії.",
      "cover": {
        "url": "https://tverdokhlibk.github.io/kostyatverdokhlib.github.io-blw-blog/images/allergy.webp",
        "caption": "Мама пропонує немовляті алергенний продукт у безпечній кількості."
      },
      "blocks": [
        {
          "type": "paragraph",
          "data": {
            "text": "Алергія у дітей — одна з найпоширеніших проблем раннього віку."
          }
        },
        {
          "type": "paragraph",
          "data": {
            "text": "Колись батькам радили відкладати знайомство з алергенними продуктами, але сучасні дослідження демонструють протилежне: своєчасне введення невеликих порцій допомагає імунній системі звикнути до нових речовин."
          }
        },
        {
          "type": "divider"
        },
        {
          "type": "heading",
          "data": {
            "text": "Сучасний підхід"
          }
        },
        {
          "type": "paragraph",
          "data": {
            "text": "Міжнародні організації — ВООЗ, ESPGHAN та Американська академія педіатрії — радять знайомити малюка з алергенами приблизно з 6 місяців, коли він готовий до твердої їжі."
          }
        },
        {
          "type": "paragraph",
          "data": {
            "text": "\"Раннє знайомство з контрольованими порціями алергенів формує імунну толерантність\" — на цьому наголошують дитячі алергологи. Тому важливо вводити нові продукти, коли дитина здорова, без висипань чи застуди."
          }
        },
        {
          "type": "paragraph",
          "data": {
            "text": "Щоб відстежити реакцію, нові інгредієнти пропонують по одному та у першій половині дня."
          }
        },
        {
          "type": "divider"
        },
        {
          "type": "heading",
          "data": {
            "text": "Основні харчові алергени"
          }
        },
        {
          "type": "paragraph",
          "data": {
            "text": "У ЄС офіційно виділяють 14 груп харчових алергенів: глютен, арахіс, горіхи, селера, гірчиця, молоко, яйця, кунжут, риба, ракоподібні, молюски, соя, сульфіти та люпін."
          }
        },
        {
          "type": "paragraph",
          "data": {
            "text": "Для українських сімей найактуальнішими під час прикорму є яйця, риба, молоко, пшениця, соя, арахіс, селера, різні горіхи та кунжут."
          }
        },
        {
          "type": "divider"
        },
        {
          "type": "heading",
          "data": {
            "text": "Як починати знайомство з алергенами"
          }
        },
        {
          "type": "paragraph",
          "data": {
            "text": "Додавайте алергени, коли базові продукти — овочі, каші, м’ясо — вже введені та добре переносяться."
          }
        },
        {
          "type": "paragraph",
          "data": {
            "text": "• Починайте з мікропорцій — 1/4 чайної ложки або кількох крупинок."
          }
        },
        {
          "type": "paragraph",
          "data": {
            "text": "• Якщо реакції немає, поступово збільшуйте кількість протягом кількох днів."
          }
        },
        {
          "type": "paragraph",
          "data": {
            "text": "• Ведіть щоденник прикорму, щоб фіксувати дату, кількість та спостереження."
          }
        },
        {
          "type": "divider"
        },
        {
          "type": "heading",
          "data": {
            "text": "Як безпечно вводити алергени"
          }
        },
        {
          "type": "paragraph",
          "data": {
            "text": "1. Один новий продукт за раз — так легше знайти причину реакції."
          }
        },
        {
          "type": "paragraph",
          "data": {
            "text": "2. Починайте з мінімальної кількості та пропонуйте алерген вдень."
          }
        },
        {
          "type": "paragraph",
          "data": {
            "text": "3. Робіть паузу в 3 дні перед наступним новим продуктом."
          }
        },
        {
          "type": "paragraph",
          "data": {
            "text": "4. Якщо алерген добре переноситься, повторюйте його 1–2 рази на тиждень, щоб закріпити толерантність."
          }
        },
        {
          "type": "divider"
        },
        {
          "type": "heading",
          "data": {
            "text": "Можливі прояви алергії"
          }
        },
        {
          "type": "paragraph",
          "data": {
            "text": "Ознаки реакції можуть включати почервоніння навколо рота, висип, набряк губ чи повік, кашель, чхання, утруднене дихання, блювання, діарею або різку примхливість."
          }
        },
        {
          "type": "paragraph",
          "data": {
            "text": "При появі утрудненого дихання, набряку обличчя чи голосових зв’язок негайно зверніться по медичну допомогу."
          }
        },
        {
          "type": "divider"
        },
        {
          "type": "heading",
          "data": {
            "text": "Якщо алергія вже була"
          }
        },
        {
          "type": "paragraph",
          "data": {
            "text": "Не повторюйте спробу без консультації з педіатром або алергологом. Лікар підкаже, чи варто проходити провокаційні проби і коли це робити."
          }
        },
        {
          "type": "paragraph",
          "data": {
            "text": "Деякі діти «переростають» алергію, але шлях до цього має бути безпечним і контрольованим."
          }
        },
        {
          "type": "divider"
        },
        {
          "type": "heading",
          "data": {
            "text": "Головна думка"
          }
        },
        {
          "type": "paragraph",
          "data": {
            "text": "Алергенні продукти не вороги, якщо вводити їх розумно. Поступове і контрольоване знайомство допомагає сформувати здорові харчові звички та зменшує ризик алергії в майбутньому."
          }
        }
      ]
    }
  ]
}
